ptl_si/PTL_SI.py
ptl_si/__init__.py
ptl_si/gen_data.py
ptl_si/sub_prob.py
ptl_si/transfer_learning_hdr.py
ptl_si/utils.py
ptl_si-0.1.0.dist-info/LICENSE
ptl_si-0.1.0.dist-info/METADATA
ptl_si-0.1.0.dist-info/WHEEL
ptl_si-0.1.0.dist-info/top_level.txt
ptl_si-0.1.0.dist-info/RECORD
