Metadata-Version: 2.1
Name: ptl-si
Version: 0.1.0
Summary: PTL-SI: Statistical inference for high-dimensional regression after transfer learning
Home-page: https://github.com/22520896/PTL_SI
Author: Nguyen Vu Khai Tam, Cao Huyen My, Vo Nguyen Le Duy
Author-email: 22521293@gm.uit.edu.vn, 22520896@gm.uit.edu.vn, duyvnl@uit.edu.vn
Classifier: Programming Language :: Python :: 3
Classifier: License :: OSI Approved :: MIT License
Classifier: Operating System :: OS Independent
Requires-Python: >=3.6
License-File: LICENSE
Requires-Dist: numpy
Requires-Dist: scipy
Requires-Dist: mpmath
Requires-Dist: skglm
